pyidverify/__init__.py
pyidverify/_version.py
pyidverify/config/__init__.py
pyidverify/config/countries.py
pyidverify/config/loader.py
pyidverify/config/patterns.py
pyidverify/config/settings.py
pyidverify/core/__init__.py
pyidverify/core/base_validator.py
pyidverify/core/biometric_engine.py
pyidverify/core/biometric_types.py
pyidverify/core/engine.py
pyidverify/core/exceptions.py
pyidverify/core/interfaces.py
pyidverify/core/types.py
pyidverify/core/validation_engine.py
pyidverify/core/validator_factory.py
pyidverify/email_verification/IMPLEMENTATION_COMPLETE.md
pyidverify/email_verification/__init__.py
pyidverify/email_verification/api_verifier.py
pyidverify/email_verification/behavioral_verifier.py
pyidverify/email_verification/enhanced_dns.py
pyidverify/email_verification/enhanced_email_validator.py
pyidverify/email_verification/hybrid_verifier.py
pyidverify/email_verification/smtp_verifier.py
pyidverify/monitoring/health.py
pyidverify/monitoring/metrics_collector.py
pyidverify/security/__init__.py
pyidverify/security/audit.py
pyidverify/security/audit_logger.py
pyidverify/security/compliance.py
pyidverify/security/constants.py
pyidverify/security/encryption.py
pyidverify/security/exceptions.py
pyidverify/security/hashing.py
pyidverify/security/memory.py
pyidverify/security/rate_limiter.py
pyidverify/security/sanitization.py
pyidverify/security/tokenization.py
pyidverify/validators/__init__.py
pyidverify/validators/biometric/__init__.py
pyidverify/validators/biometric/behavioral/__init__.py
pyidverify/validators/biometric/hybrid/__init__.py
pyidverify/validators/biometric/hybrid/continuous_auth_validator.py
pyidverify/validators/biometric/hybrid/multi_factor_validator.py
pyidverify/validators/biometric/hybrid/risk_based_validator.py
pyidverify/validators/biometric/physiological/__init__.py
pyidverify/validators/custom/__init__.py
pyidverify/validators/custom/composite_validator.py
pyidverify/validators/custom/regex_validator.py
pyidverify-0.0.1a0.dist-info/METADATA
pyidverify-0.0.1a0.dist-info/WHEEL
pyidverify-0.0.1a0.dist-info/entry_points.txt
pyidverify-0.0.1a0.dist-info/licenses/LICENSE
pyidverify-0.0.1a0.dist-info/RECORD
