Metadata-Version: 2.4
Name: pyidverify
Version: 0.0.1a0
Summary: Pre-release placeholder for pyidverify. Not production ready. Enterprise-grade ID verification library with military-level security
Project-URL: Homepage, https://github.com/pyidverify/pyidverify
Project-URL: Documentation, https://pyidverify.readthedocs.io
Project-URL: Repository, https://github.com/pyidverify/pyidverify.git
Project-URL: Bug Tracker, https://github.com/pyidverify/pyidverify/issues
Project-URL: Changelog, https://github.com/pyidverify/pyidverify/blob/main/CHANGELOG.md
Project-URL: Security Policy, https://github.com/pyidverify/pyidverify/blob/main/SECURITY.md
Author: HWDigi
Maintainer: HWDigi
License: MIT
License-File: LICENSE
Keywords: compliance,credit-card,email,encryption,gdpr,hipaa,id-verification,pci-dss,phone,security,ssn,validation
Classifier: Development Status :: 4 - Beta
Classifier: Intended Audience :: Developers
Classifier: Intended Audience :: Financial and Insurance Industry
Classifier: Intended Audience :: Healthcare Industry
Classifier: License :: OSI Approved :: MIT License
Classifier: Operating System :: OS Independent
Classifier: Programming Language :: Python :: 3
Classifier: Programming Language :: Python :: 3.8
Classifier: Programming Language :: Python :: 3.9
Classifier: Programming Language :: Python :: 3.10
Classifier: Programming Language :: Python :: 3.11
Classifier: Programming Language :: Python :: 3.12
Classifier: Topic :: Office/Business :: Financial
Classifier: Topic :: Security :: Cryptography
Classifier: Topic :: Software Development :: Libraries :: Python Modules
Classifier: Typing :: Typed
Requires-Python: >=3.8
Requires-Dist: argon2-cffi>=23.0.0
Requires-Dist: cryptography>=41.0.0
Requires-Dist: email-validator>=2.0.0
Requires-Dist: httpx>=0.24.0
Requires-Dist: phonenumbers>=8.13.0
Requires-Dist: pydantic>=2.0.0
Requires-Dist: python-dateutil>=2.8.0
Requires-Dist: redis>=4.5.0
Requires-Dist: typing-extensions>=4.5.0; python_version < '3.10'
Provides-Extra: all
Requires-Dist: celery>=5.3.0; extra == 'all'
Requires-Dist: click>=8.1.0; extra == 'all'
Requires-Dist: kombu>=5.3.0; extra == 'all'
Requires-Dist: numpy>=1.24.0; extra == 'all'
Requires-Dist: opentelemetry-api>=1.17.0; extra == 'all'
Requires-Dist: opentelemetry-instrumentation>=0.38b0; extra == 'all'
Requires-Dist: opentelemetry-sdk>=1.17.0; extra == 'all'
Requires-Dist: pandas>=2.0.0; extra == 'all'
Requires-Dist: prometheus-client>=0.16.0; extra == 'all'
Requires-Dist: prompt-toolkit>=3.0.0; extra == 'all'
Requires-Dist: psycopg2-binary>=2.9.0; extra == 'all'
Requires-Dist: pygments>=2.15.0; extra == 'all'
Requires-Dist: pymongo>=4.3.0; extra == 'all'
Requires-Dist: redis>=4.5.0; extra == 'all'
Requires-Dist: rich>=13.0.0; extra == 'all'
Requires-Dist: scikit-learn>=1.3.0; extra == 'all'
Requires-Dist: sqlalchemy>=2.0.0; extra == 'all'
Requires-Dist: tensorflow>=2.12.0; extra == 'all'
Requires-Dist: torch>=2.0.0; extra == 'all'
Requires-Dist: transformers>=4.30.0; extra == 'all'
Provides-Extra: cli
Requires-Dist: click>=8.1.0; extra == 'cli'
Requires-Dist: prompt-toolkit>=3.0.0; extra == 'cli'
Requires-Dist: pygments>=2.15.0; extra == 'cli'
Requires-Dist: rich>=13.0.0; extra == 'cli'
Provides-Extra: database
Requires-Dist: psycopg2-binary>=2.9.0; extra == 'database'
Requires-Dist: pymongo>=4.3.0; extra == 'database'
Requires-Dist: sqlalchemy>=2.0.0; extra == 'database'
Provides-Extra: dev
Requires-Dist: bandit>=1.7.0; extra == 'dev'
Requires-Dist: black>=23.0.0; extra == 'dev'
Requires-Dist: build>=0.10.0; extra == 'dev'
Requires-Dist: flake8>=6.0.0; extra == 'dev'
Requires-Dist: hypothesis>=6.70.0; extra == 'dev'
Requires-Dist: isort>=5.12.0; extra == 'dev'
Requires-Dist: mypy>=1.0.0; extra == 'dev'
Requires-Dist: myst-parser>=2.0.0; extra == 'dev'
Requires-Dist: pre-commit>=3.0.0; extra == 'dev'
Requires-Dist: pytest-asyncio>=0.21.0; extra == 'dev'
Requires-Dist: pytest-cov>=4.0.0; extra == 'dev'
Requires-Dist: pytest-xdist>=3.0.0; extra == 'dev'
Requires-Dist: pytest>=7.0.0; extra == 'dev'
Requires-Dist: safety>=2.3.0; extra == 'dev'
Requires-Dist: semgrep>=1.0.0; extra == 'dev'
Requires-Dist: sphinx-rtd-theme>=1.3.0; extra == 'dev'
Requires-Dist: sphinx>=7.0.0; extra == 'dev'
Requires-Dist: twine>=4.0.0; extra == 'dev'
Provides-Extra: ml
Requires-Dist: numpy>=1.24.0; extra == 'ml'
Requires-Dist: pandas>=2.0.0; extra == 'ml'
Requires-Dist: scikit-learn>=1.3.0; extra == 'ml'
Provides-Extra: ml-advanced
Requires-Dist: tensorflow>=2.12.0; extra == 'ml-advanced'
Requires-Dist: torch>=2.0.0; extra == 'ml-advanced'
Requires-Dist: transformers>=4.30.0; extra == 'ml-advanced'
Provides-Extra: monitoring
Requires-Dist: opentelemetry-api>=1.17.0; extra == 'monitoring'
Requires-Dist: opentelemetry-instrumentation>=0.38b0; extra == 'monitoring'
Requires-Dist: opentelemetry-sdk>=1.17.0; extra == 'monitoring'
Requires-Dist: prometheus-client>=0.16.0; extra == 'monitoring'
Provides-Extra: queue
Requires-Dist: celery>=5.3.0; extra == 'queue'
Requires-Dist: kombu>=5.3.0; extra == 'queue'
Requires-Dist: redis>=4.5.0; extra == 'queue'
